pystratos/__init__.py
pystratos/ipfs.py
pystratos/spfs.py
pystratos-0.1.1.dist-info/LICENSE.md
pystratos-0.1.1.dist-info/METADATA
pystratos-0.1.1.dist-info/WHEEL
pystratos-0.1.1.dist-info/RECORD
